<?xml version="1.0" encoding="UTF-8"?>
<cars>
	<car xmlns="https://www.letslearnmule.com">
   	   <variant>sedan/suv</variant>
	   <car> 
	   		<brand model="Altima">Nissan</brand> 
	   		<years> 
	   			<variant>sedan</variant>
	   			<year>2019</year> 
	   			<year>2020</year> 
	   		</years> 
	   	</car>
	   <car> 
	   		<brand model="Model S">Tesla</brand> 
	   		<variant>sedan</variant>
	   		<years> 
	   			<year>2019</year> 
	   			<year>2020</year> 
	   		</years> 
	   	</car>
   	</car>
</cars>